{
  "songs": [
    {
      "title": "Ledger Lines Test - All Notes",
      "clef": "treble",
      "timeSignature": "4/4",
      "keySignature": "",
      "notes": [ "C3:4", "D3:4", "E3:4", "F3:4", "G3:4", "A3:4", "B3:4", "C4:4", "D4:4", "E4:4" ]
    },
    {
      "title": "♯7: C# Major (F#, C#, G#, D#, A#, E#, B#)",
      "clef": "treble",
      "timeSignature": "4/4",
      "keySignature": "F#,C#,G#,D#,A#,E#,B#",
      "notes": [ "C#4:4", "D#4:4", "E#4:4", "F#4:4", "G#4:4", "A#4:4", "B#4:4", "C#5:4" ]
    },
    {
      "title": "♯7: C# Major (F#, C#, G#, D#, A#, E#, B#)",
      "clef": "bass",
      "timeSignature": "4/4",
      "keySignature": "F#,C#,G#,D#,A#,E#,B#",
      "notes": [ "C#4:4", "D#4:4", "E#4:4", "F#4:4", "G#4:4", "A#4:4", "B#4:4", "C#5:4" ]
    },
    {
      "title": "♭7: Cb Major (Bb, Eb, Ab, Db, Gb, Cb, Fb)",
      "clef": "treble",
      "timeSignature": "4/4",
      "keySignature": "Bb,Eb,Ab,Db,Gb,Cb,Fb",
      "notes": [ "Cb4:4", "Db4:4", "Eb4:4", "Fb4:4", "Gb4:4", "Ab4:4", "Bb4:4", "Cb5:4" ]
    },
    {
      "title": "♭7: Cb Major (Bb, Eb, Ab, Db, Gb, Cb, Fb)",
      "clef": "bass",
      "timeSignature": "4/4",
      "keySignature": "Bb,Eb,Ab,Db,Gb,Cb,Fb",
      "notes": [ "Cb4:4", "Db4:4", "Eb4:4", "Fb4:4", "Gb4:4", "Ab4:4", "Bb4:4", "Cb5:4" ]
    }
  ]
}