{
  "songs": [
    {
      "title": "F 장조 (플랫 1개: Bb)",
      "clef": "Treble",
      "key": "F",
      "time": "4/4",
      "notes": [ "B3:1", "C4:1", "D4:1", "E4:1", "F4:1", "G4:1", "A4:1", "B4:1" ]
    },
    {
      "title": "Bb 장조 (플랫 2개: Bb, Eb)",
      "clef": "Treble",
      "key": "Bb",
      "time": "4/4",
      "notes": [ "E3:1", "F3:1", "G3:1", "A3:1", "B3:1", "C4:1", "D4:1", "E4:1" ]
    },
    {
      "title": "Eb 장조 (플랫 3개: Bb, Eb, Ab)",
      "clef": "Treble",
      "key": "Eb",
      "time": "4/4",
      "notes": [ "A3:1", "B3:1", "C4:1", "D4:1", "E4:1", "F4:1", "G4:1", "A4:1" ]
    },
    {
      "title": "Ab 장조 (플랫 4개: Bb, Eb, Ab, Db)",
      "clef": "Treble",
      "key": "Ab",
      "time": "4/4",
      "notes": [ "D4:1", "E4:1", "F4:1", "G4:1", "A4:1", "B4:1", "C5:1", "D5:1" ]
    },
    {
      "title": "Db 장조 (플랫 5개: Bb, Eb, Ab, Db, Gb)",
      "clef": "Treble",
      "key": "Db",
      "time": "4/4",
      "notes": [ "G3:1", "A3:1", "B3:1", "C4:1", "D4:1", "E4:1", "F4:1", "G4:1" ]
    },
    {
      "title": "Gb 장조 (플랫 6개: Bb, Eb, Ab, Db, Gb, Cb)",
      "clef": "Treble",
      "key": "Gb",
      "time": "4/4",
      "notes": [ "C4:1", "D4:1", "E4:1", "F4:1", "G4:1", "A4:1", "B4:1", "C5:1" ]
    },
    {
      "title": "Cb 장조 (플랫 7개: Bb, Eb, Ab, Db, Gb, Cb, Fb)",
      "clef": "Treble",
      "key": "Cb",
      "time": "4/4",
      "notes": [ "F3:1", "G3:1", "A3:1", "B3:1", "C4:1", "D4:1", "E4:1", "F4:1" ]
    }
  ]
}
